<?xml version="1.0" encoding="utf-8"?>
<doctrine-mapping xmlns="http://doctrine-project.org/schemas/orm/doctrine-mapping" xmlns:xsi="http://www.w3.org/2001/XMLSchema-instance" xsi:schemaLocation="http://doctrine-project.org/schemas/orm/doctrine-mapping http://doctrine-project.org/schemas/orm/doctrine-mapping.xsd">
  <entity name="AppBundle\Entity\Tiposeguro" table="tiposeguro">
    <id name="idtiposeguro" type="integer" column="idtiposeguro">
      <generator strategy="IDENTITY"/>
    </id>
    <field name="descripcion" type="text" column="descripcion" length="65535" nullable="true">
      <options>
        <option name="fixed"/>
      </options>
    </field>
    <field name="razon" type="string" column="razon" length="10" nullable="true">
      <options>
        <option name="fixed"/>
      </options>
    </field>
  </entity>
</doctrine-mapping>
